setup.py
cloudify.egg-info/PKG-INFO
cloudify.egg-info/SOURCES.txt
cloudify.egg-info/dependency_links.txt
cloudify.egg-info/entry_points.txt
cloudify.egg-info/requires.txt
cloudify.egg-info/top_level.txt
cloudify_cli/VERSION
cloudify_cli/__init__.py
cloudify_cli/blueprint.py
cloudify_cli/colorful_event.py
cloudify_cli/constants.py
cloudify_cli/env.py
cloudify_cli/exceptions.py
cloudify_cli/execution_events_fetcher.py
cloudify_cli/inputs.py
cloudify_cli/local.py
cloudify_cli/logger.py
cloudify_cli/main.py
cloudify_cli/ssh.py
cloudify_cli/table.py
cloudify_cli/utils.py
cloudify_cli/cli/__init__.py
cloudify_cli/cli/cfy.py
cloudify_cli/cli/completion_utils.py
cloudify_cli/cli/helptexts.py
cloudify_cli/commands/__init__.py
cloudify_cli/commands/agents.py
cloudify_cli/commands/blueprints.py
cloudify_cli/commands/cluster.py
cloudify_cli/commands/deployments.py
cloudify_cli/commands/dev.py
cloudify_cli/commands/events.py
cloudify_cli/commands/executions.py
cloudify_cli/commands/groups.py
cloudify_cli/commands/init.py
cloudify_cli/commands/install.py
cloudify_cli/commands/ldap.py
cloudify_cli/commands/logs.py
cloudify_cli/commands/maintenance_mode.py
cloudify_cli/commands/node_instances.py
cloudify_cli/commands/nodes.py
cloudify_cli/commands/plugins.py
cloudify_cli/commands/profiles.py
cloudify_cli/commands/secrets.py
cloudify_cli/commands/snapshots.py
cloudify_cli/commands/ssh.py
cloudify_cli/commands/ssl_cmd.py
cloudify_cli/commands/status.py
cloudify_cli/commands/tenants.py
cloudify_cli/commands/tokens.py
cloudify_cli/commands/uninstall.py
cloudify_cli/commands/user_groups.py
cloudify_cli/commands/users.py
cloudify_cli/commands/workflows.py
cloudify_cli/config/__init__.py
cloudify_cli/config/config.py
cloudify_cli/config/config_template.yaml