Metadata-Version: 1.0
Name: cloudify
Version: 18.10.4
Summary: Cloudify's Command Line Interface
Home-page: UNKNOWN
Author: Gigaspaces
Author-email: cosmo-admin@gigaspaces.com
License: LICENSE
Platform: UNKNOWN
